chronomap/__init__.py
chronomap/__main__.py
chronomap/chronomap.py
chronomap/cli.py
chronomap-2.1.1.dist-info/licenses/LICENSE
logo/logo.png
tests/test_chronomap.py
chronomap-2.1.1.dist-info/METADATA
chronomap-2.1.1.dist-info/WHEEL
chronomap-2.1.1.dist-info/top_level.txt
chronomap-2.1.1.dist-info/RECORD
