Metadata-Version: 2.4
Name: chronomap
Version: 2.1.1
Summary: Enhanced thread-safe, time-versioned key-value store with snapshots, queries, async, and more.
Author-email: Devansh Singh <devansh.jay.singh@gmail.com>
License: MIT
Project-URL: Homepage, https://github.com/Devansh-567/chronomap
Project-URL: Icon, https://raw.githubusercontent.com/Devansh-567/Chronomap/main/logo/logo.png
Keywords: chronomap,timestamp,key-value,time-series,snapshot,async,rwlock
Classifier: Programming Language :: Python :: 3
Classifier: License :: OSI Approved :: MIT License
Classifier: Operating System :: OS Independent
Classifier: Development Status :: 5 - Production/Stable
Requires-Python: >=3.8
License-File: LICENSE
Provides-Extra: pandas
Requires-Dist: pandas; extra == "pandas"
Dynamic: license-file
Dynamic: requires-python
